{
    "_2ship2harkinian": {
        "cargoLock": null,
        "date": null,
        "extract": null,
        "name": "_2ship2harkinian",
        "passthru": null,
        "pinned": false,
        "src": {
            "deepClone": false,
            "fetchSubmodules": true,
            "leaveDotGit": false,
            "name": null,
            "rev": "4.0.2",
            "sha256": "sha256-3SgRvQL27e+MoTBGX4/iUwgELd6UFbjrb23gV1UvAJ8=",
            "sparseCheckout": [],
            "type": "git",
            "url": "https://github.com/HarbourMasters/2ship2harkinian.git"
        },
        "version": "4.0.2"
    },
    "fluxer-desktop": {
        "cargoLock": null,
        "date": null,
        "extract": null,
        "name": "fluxer-desktop",
        "passthru": null,
        "pinned": false,
        "src": {
            "name": null,
            "sha256": "sha256-rPY5j6aBByD+2FsGwBGzJOfbT+xr8vx62TwkRsNgDy0=",
            "type": "url",
            "url": "https://api.fluxer.app/dl/desktop/stable/linux/x64/latest/tar_gz"
        },
        "version": "0.0.8"
    },
    "fluxer-desktop-canary": {
        "cargoLock": null,
        "date": null,
        "extract": null,
        "name": "fluxer-desktop-canary",
        "passthru": null,
        "pinned": false,
        "src": {
            "name": null,
            "sha256": "sha256-IhzEcYaCcClCO/qIYkEo2JsTLEB+K0+cQWCaJO1Zz7A=",
            "type": "url",
            "url": "https://api.canary.fluxer.app/dl/desktop/canary/linux/x64/latest/tar_gz"
        },
        "version": "2026.602.31138"
    },
    "hytale-launcher": {
        "cargoLock": null,
        "date": null,
        "extract": null,
        "name": "hytale-launcher",
        "passthru": null,
        "pinned": false,
        "src": {
            "name": null,
            "sha256": "sha256-qC5q+5DRkl0jqmPRdWlcZ9n0sYKQdwmPncL/It9FhMw=",
            "type": "url",
            "url": "https://launcher.hytale.com/builds/release/linux/amd64/hytale-launcher-2026.07.07-325d709.zip"
        },
        "version": "2026.07.07-325d709"
    },
    "jellium-desktop": {
        "cargoLock": null,
        "date": "2026-07-17",
        "extract": null,
        "name": "jellium-desktop",
        "passthru": null,
        "pinned": false,
        "src": {
            "deepClone": false,
            "fetchSubmodules": false,
            "leaveDotGit": false,
            "name": null,
            "rev": "1272c89883c72453e1632f077336729c7d34ad16",
            "sha256": "sha256-ippLfD7ROO4PUJGSSkk8CCiZFCPLpVNEFrF+ApRBir8=",
            "sparseCheckout": [],
            "type": "git",
            "url": "https://github.com/andrewrabert/jellium-desktop.git"
        },
        "version": "1272c89883c72453e1632f077336729c7d34ad16"
    },
    "libdrm": {
        "cargoLock": null,
        "date": "2026-07-14",
        "extract": null,
        "name": "libdrm",
        "passthru": null,
        "pinned": false,
        "src": {
            "deepClone": false,
            "fetchSubmodules": false,
            "leaveDotGit": false,
            "name": null,
            "rev": "f9816a42b0d6138851cbe5eb7a33ee1a2f2a15ca",
            "sha256": "sha256-jljFpM2GMXLBY5bDibk6bIobSNfxhW8duRNacSvXK7M=",
            "sparseCheckout": [],
            "type": "git",
            "url": "https://gitlab.freedesktop.org/mesa/drm.git"
        },
        "version": "f9816a42b0d6138851cbe5eb7a33ee1a2f2a15ca"
    },
    "mesa": {
        "cargoLock": null,
        "date": "2026-07-18",
        "extract": null,
        "name": "mesa",
        "passthru": null,
        "pinned": false,
        "src": {
            "deepClone": false,
            "fetchSubmodules": false,
            "leaveDotGit": false,
            "name": null,
            "rev": "db128e2f552610de79e2912925929c40c9a55652",
            "sha256": "sha256-mvXtyeu5o32UcdofcSO0N1a/hC3Ui88soo4ow+b5k3k=",
            "sparseCheckout": [],
            "type": "git",
            "url": "https://gitlab.freedesktop.org/mesa/mesa.git"
        },
        "version": "db128e2f552610de79e2912925929c40c9a55652"
    },
    "modengine3": {
        "cargoLock": null,
        "date": null,
        "extract": null,
        "name": "modengine3",
        "passthru": null,
        "pinned": false,
        "src": {
            "name": null,
            "sha256": "sha256-NWx/SF7aKN8S7/Jvp5T5U0oOQyE0DKzy9EUJGHOoH78=",
            "type": "url",
            "url": "https://github.com/garyttierney/me3/releases/download/v0.12.0/me3-linux-amd64.tar.gz"
        },
        "version": "v0.12.0"
    },
    "oodle-lib": {
        "cargoLock": null,
        "date": null,
        "extract": null,
        "name": "oodle-lib",
        "passthru": null,
        "pinned": false,
        "src": {
            "name": null,
            "sha256": "sha256-c1RlXrJbWH3DTL+YaWuR4w5tej8O7604cubBt274am4=",
            "type": "url",
            "url": "https://github.com/new-world-tools/go-oodle/releases/download/v0.2.3-files/liboo2corelinux64.so.9"
        },
        "version": "0.2.3"
    },
    "opengoal-launcher": {
        "cargoLock": null,
        "date": null,
        "extract": null,
        "name": "opengoal-launcher",
        "passthru": null,
        "pinned": false,
        "src": {
            "name": null,
            "sha256": "sha256-eikzjdOYNdJM9FM3O/HuCFDzf97Fm1nhbRedDyKZ1/s=",
            "type": "url",
            "url": "https://github.com/open-goal/launcher/releases/download/v2.10.4/OpenGOAL-Launcher_2.10.4_amd64.AppImage"
        },
        "version": "2.10.4"
    },
    "pokemmo": {
        "cargoLock": null,
        "date": null,
        "extract": null,
        "name": "pokemmo",
        "passthru": null,
        "pinned": false,
        "src": {
            "name": null,
            "sha256": "sha256-8foFB6p3K0Ija9ZQ+oam1tcGFka4wSJSOOOvtr6ydbU=",
            "type": "url",
            "url": "https://pokemmo.com/download_file/1/"
        },
        "version": "100884776"
    },
    "proton-cachyos": {
        "cargoLock": null,
        "date": null,
        "extract": null,
        "name": "proton-cachyos",
        "passthru": null,
        "pinned": false,
        "src": {
            "name": null,
            "sha256": "sha256-Qo16R7KVGYVuW61Q634PASPsJDHi03wxzr7ycD8k8lM=",
            "type": "url",
            "url": "https://github.com/CachyOS/proton-cachyos/releases/download/cachyos-11.0-20260702-slr/proton-cachyos-11.0-20260702-slr-x86_64.tar.xz"
        },
        "version": "cachyos-11.0-20260702-slr"
    },
    "proton-cachyos-x86_64-v3": {
        "cargoLock": null,
        "date": null,
        "extract": null,
        "name": "proton-cachyos-x86_64-v3",
        "passthru": null,
        "pinned": false,
        "src": {
            "name": null,
            "sha256": "sha256-ETl4U+uV+PtEhTXOviZVRxMGyAw0VsRrUs1Whwik/lw=",
            "type": "url",
            "url": "https://github.com/CachyOS/proton-cachyos/releases/download/cachyos-11.0-20260702-slr/proton-cachyos-11.0-20260702-slr-x86_64_v3.tar.xz"
        },
        "version": "cachyos-11.0-20260702-slr"
    },
    "pseudoregalia-rando": {
        "cargoLock": null,
        "date": null,
        "extract": null,
        "name": "pseudoregalia-rando",
        "passthru": null,
        "pinned": false,
        "src": {
            "name": null,
            "sha256": "sha256-viI3nxgwdTxH3m4dG564Lay45Q2m1AUlelYsABAdt/Q=",
            "type": "url",
            "url": "https://github.com/pseudoregalia-modding/rando/archive/1.8.6.tar.gz"
        },
        "version": "1.8.6"
    },
    "shipwright": {
        "cargoLock": null,
        "date": null,
        "extract": null,
        "name": "shipwright",
        "passthru": null,
        "pinned": false,
        "src": {
            "deepClone": false,
            "fetchSubmodules": true,
            "leaveDotGit": false,
            "name": null,
            "rev": "9.2.3",
            "sha256": "sha256-tu6hS9Q/np4QqVHlI50QmhSOeVTO3RKolO2F2iSiU7Q=",
            "sparseCheckout": [],
            "type": "git",
            "url": "https://github.com/harbourmasters/shipwright.git"
        },
        "version": "9.2.3"
    },
    "vencord": {
        "cargoLock": null,
        "date": "2026-07-17",
        "extract": null,
        "name": "vencord",
        "passthru": null,
        "pinned": false,
        "src": {
            "deepClone": false,
            "fetchSubmodules": false,
            "leaveDotGit": false,
            "name": null,
            "rev": "0a5dfaa1caa0799899b4d14e3862b70c665d8223",
            "sha256": "sha256-5j2BN51toR9ygtcL+DLChTdeGjoVjo8uBNjI86Q2wgY=",
            "sparseCheckout": [],
            "type": "git",
            "url": "https://github.com/Vendicated/Vencord.git"
        },
        "version": "0a5dfaa1caa0799899b4d14e3862b70c665d8223"
    },
    "vintagestory": {
        "cargoLock": null,
        "date": null,
        "extract": null,
        "name": "vintagestory",
        "passthru": null,
        "pinned": false,
        "src": {
            "name": null,
            "sha256": "sha256-sa4Pj1DwT6W6LJCAYznmbyqPtMUTaLSNTkXS1imQp04=",
            "type": "url",
            "url": "https://cdn.vintagestory.at/gamefiles/stable/vs_client_linux-x64_1.22.3.tar.gz"
        },
        "version": "stable/vs_client_linux-x64_1.22.3"
    },
    "wayland": {
        "cargoLock": null,
        "date": null,
        "extract": null,
        "name": "wayland",
        "passthru": null,
        "pinned": false,
        "src": {
            "deepClone": false,
            "fetchSubmodules": false,
            "leaveDotGit": false,
            "name": null,
            "rev": "1.26.0",
            "sha256": "sha256-dnaXYcVfc4DfNRsAEL316eSTen9tpf+nuQbActege4E=",
            "sparseCheckout": [],
            "type": "git",
            "url": "https://gitlab.freedesktop.org/wayland/wayland.git"
        },
        "version": "1.26.0"
    },
    "wayland-protocols": {
        "cargoLock": null,
        "date": "2026-06-23",
        "extract": null,
        "name": "wayland-protocols",
        "passthru": null,
        "pinned": false,
        "src": {
            "deepClone": false,
            "fetchSubmodules": false,
            "leaveDotGit": false,
            "name": null,
            "rev": "afb614d5fcbd02d261a6ae91920aa91cf3915a8a",
            "sha256": "sha256-EgUVZoH2V9suDICELRgrjNi7NqCRu9LjxDSE3VNgSz0=",
            "sparseCheckout": [],
            "type": "git",
            "url": "https://gitlab.freedesktop.org/wayland/wayland-protocols.git"
        },
        "version": "afb614d5fcbd02d261a6ae91920aa91cf3915a8a"
    }
}